README.md
setup.py
pat/__init__.py
pat/data.py
pat/pose_sync.py
pat/utils.py
pat/version.py
pat/resources/impute_weights.hdf5
pat/resources/standardfig.csv
py_pat.egg-info/PKG-INFO
py_pat.egg-info/SOURCES.txt
py_pat.egg-info/dependency_links.txt
py_pat.egg-info/requires.txt
py_pat.egg-info/top_level.txt